mst/googlelib/GoogleSDK.py
mst/googlelib/__init__.py
mst/googlelib/lazy_load.py
mst/googlelib/models/__init__.py
mst/googlelib/models/group.py
mst/googlelib/models/member.py
mst/googlelib/models/user.py
mst_google-2.0.0.dev1695848807.dist-info/METADATA
mst_google-2.0.0.dev1695848807.dist-info/WHEEL
mst_google-2.0.0.dev1695848807.dist-info/top_level.txt
mst_google-2.0.0.dev1695848807.dist-info/RECORD
