Metadata-Version: 2.1
Name: mst-google
Version: 2.0.0.dev1695848807
Summary: A wrapper around the Google Admin SDK for Group management
Author-email: Missouri University of Science and Technology - Information Technology <it-ai@mst.edu>
Requires-Python: >=3.11
Requires-Dist: google-auth-oauthlib
Requires-Dist: google-api-python-client
Requires-Dist: mst-core
